Metadata-Version: 2.1
Name: argbind
Version: 0.3.9
Summary: Simple way to bind function arguments to the command line.
Home-page: https://github.com/pseeth/argbind/
Author: Prem Seetharaman
Author-email: prem@descript.com
Keywords: command-line configuration yaml argument parsing
Classifier: License :: OSI Approved :: MIT License
Classifier: Development Status :: 3 - Alpha
Classifier: Programming Language :: Python :: 3.6
Classifier: Programming Language :: Python :: 3.7
Classifier: Programming Language :: Python :: 3.8
Classifier: Operating System :: POSIX :: Linux
Classifier: Operating System :: MacOS
Classifier: Operating System :: Microsoft :: Windows
Requires-Python: >=3.5, <4
License-File: LICENSE.md
Requires-Dist: pyyaml
Requires-Dist: docstring-parser
Provides-Extra: tests
Requires-Dist: pytest; extra == "tests"
Requires-Dist: pytest-cov; extra == "tests"
Requires-Dist: torch; extra == "tests"
Requires-Dist: torchvision; extra == "tests"
Provides-Extra: examples
Requires-Dist: torch; extra == "examples"
Requires-Dist: torchvision; extra == "examples"
